maproxylib/__init__.py
maproxylib/fields.py
maproxylib/py.typed
maproxylib/storages.py
maproxylib/utils.py
maproxylib-0.1.2.dist-info/METADATA
maproxylib-0.1.2.dist-info/WHEEL
maproxylib-0.1.2.dist-info/licenses/LICENSE
maproxylib-0.1.2.dist-info/RECORD
