Metadata-Version: 2.4
Name: maproxylib
Version: 0.1.2
Summary: Transparent access to nested objects/dicts fields via descriptors
Author-email: Artem Netkachev <arnetkachev@yandex.ru>
License-Expression: MIT
License-File: LICENSE
Keywords: dataclass,descriptor,dictionary,fields,mapping,nested,proxy
Classifier: Development Status :: 4 - Beta
Classifier: Intended Audience :: Developers
Classifier: License :: OSI Approved :: MIT License
Classifier: Programming Language :: Python :: 3.10
Classifier: Programming Language :: Python :: 3.11
Classifier: Programming Language :: Python :: 3.12
Classifier: Programming Language :: Python :: 3.13
Classifier: Programming Language :: Python :: 3.14
Classifier: Topic :: Software Development :: Libraries
Classifier: Topic :: Utilities
Classifier: Typing :: Typed
Requires-Python: >=3.10
